{"stats": "openaigym.episode_batch.0.13864.stats.json", "videos": [["openaigym.video.0.13864.video000000.mp4", "openaigym.video.0.13864.video000000.meta.json"], ["openaigym.video.0.13864.video003333.mp4", "openaigym.video.0.13864.video003333.meta.json"], ["openaigym.video.0.13864.video006666.mp4", "openaigym.video.0.13864.video006666.meta.json"], ["openaigym.video.0.13864.video009999.mp4", "openaigym.video.0.13864.video009999.meta.json"]], "env_info": {"gym_version": "0.10.5", "env_id": "MountainCar-v0"}}